oraclebmc_cli/__init__.py
oraclebmc_cli/version.py
oraclebmc_cli/bin/bmcs_autocomplete.sh
oraclebmc_cli-2.4.19.dist-info/DESCRIPTION.rst
oraclebmc_cli-2.4.19.dist-info/LICENSE.txt
oraclebmc_cli-2.4.19.dist-info/METADATA
oraclebmc_cli-2.4.19.dist-info/RECORD
oraclebmc_cli-2.4.19.dist-info/WHEEL
oraclebmc_cli-2.4.19.dist-info/metadata.json
oraclebmc_cli-2.4.19.dist-info/top_level.txt
