Metadata-Version: 2.0
Name: oraclebmc-cli
Version: 2.4.19
Summary: Oracle Cloud Infrastructure CLI
Home-page: https://docs.us-phoenix-1.oraclecloud.com/Content/API/SDKDocs/cli.htm
Author: Oracle
Author-email: joe.levy@oracle.com
License: Universal Permissive License 1.0 or Apache License 2.0
Platform: UNKNOWN
Classifier: Development Status :: 5 - Production/Stable
Classifier: Environment :: Console
Classifier: Intended Audience :: Information Technology
Classifier: Intended Audience :: Developers
Classifier: License :: OSI Approved :: Apache Software License
Classifier: License :: OSI Approved :: Universal Permissive License (UPL)
Classifier: Programming Language :: Python :: 2.7
Classifier: Programming Language :: Python :: 3.5
Requires-Dist: oci-cli (==2.4.19)
